MANIFEST.in
README.rst
setup.py
django_trustpay.egg-info/PKG-INFO
django_trustpay.egg-info/SOURCES.txt
django_trustpay.egg-info/dependency_links.txt
django_trustpay.egg-info/requires.txt
django_trustpay.egg-info/top_level.txt
trustpay/__init__.py
trustpay/admin.py
trustpay/client.py
trustpay/forms.py
trustpay/helpers.py
trustpay/managers.py
trustpay/models.py
trustpay/settings.py
trustpay/urls.py
trustpay/views.py
trustpay/templates/trustpay/cancel_return.html
trustpay/templates/trustpay/error_return.html
trustpay/templates/trustpay/success_return.html
trustpay/templates/trustpay/helpers/form.html