Metadata-Version: 1.0
Name: django-trustpay
Version: 0.2.2
Summary: Django app for Trustpay payment gateway API.
Home-page: https://github.com/PragmaticMates/django-trustpay
Author: Pragmatic Mates
Author-email: info@pragmaticmates.com
License: BSD License
Keywords: django trustpay payment gateway API
Platform: UNKNOWN
Classifier: Programming Language :: Python
Classifier: Programming Language :: Python :: 2.5
Classifier: Programming Language :: Python :: 2.6
Classifier: Programming Language :: Python :: 2.7
Classifier: Operating System :: OS Independent
Classifier: Environment :: Web Environment
Classifier: Intended Audience :: Developers
Classifier: Framework :: Django
Classifier: License :: OSI Approved :: BSD License
Classifier: Development Status :: 3 - Alpha
